zhandegao_test_2/__init__.py
zhandegao_test_2/core.py
zhandegao_test_2-0.0.2.dist-info/METADATA
zhandegao_test_2-0.0.2.dist-info/WHEEL
zhandegao_test_2-0.0.2.dist-info/licenses/LICENSE
zhandegao_test_2-0.0.2.dist-info/RECORD
